nynoflow/__init__.py
nynoflow/chats/__init__.py
nynoflow/chats/_chatgpt/_chatgpt.py
nynoflow/chats/_chatgpt/_chatgpt_objects.py
nynoflow/chats/_gpt4all/_gpt4all.py
nynoflow/chats/_gpt4all/_gpt4all_objects.py
nynoflow/chats/chat_objects.py
nynoflow/exceptions/__init__.py
nynoflow/flow/__init__.py
nynoflow/flow/flow.py
nynoflow/function/__init__.py
nynoflow/memory/__init__.py
nynoflow/memory/azure_blob_memory.py
nynoflow/memory/base_file_memory.py
nynoflow/memory/base_memory.py
nynoflow/memory/ephermal_memory.py
nynoflow/memory/gcp_memory.py
nynoflow/memory/local_file_memory.py
nynoflow/memory/redis_memory.py
nynoflow/memory/s3_memory.py
nynoflow/memory/sqlalchemy_memory.py
nynoflow/py.typed
nynoflow/templates/__init__.py
nynoflow/templates/optional_functions.j2
nynoflow/templates/output_formatter.j2
nynoflow/templates/required_functions.j2
nynoflow/tokenizers/__init__.py
nynoflow/tokenizers/base_tokenizer.py
nynoflow/tokenizers/openai_tokenizer.py
nynoflow/util.py
nynoflow-0.3.0.dist-info/LICENSE
nynoflow-0.3.0.dist-info/METADATA
nynoflow-0.3.0.dist-info/WHEEL
nynoflow-0.3.0.dist-info/RECORD
