Metadata-Version: 2.1
Name: nynoflow
Version: 0.3.0
Summary: NynoFlow
Home-page: https://github.com/nyno-ai/nynoflow
License: GPL-3.0
Author: nyno.ai
Author-email: eitan@nyno.ai
Requires-Python: >=3.9,<4.0
Classifier: Development Status :: 3 - Alpha
Classifier: License :: OSI Approved :: GNU General Public License v3 (GPLv3)
Classifier: Programming Language :: Python :: 3
Classifier: Programming Language :: Python :: 3.9
Classifier: Programming Language :: Python :: 3.10
Classifier: Programming Language :: Python :: 3.11
Requires-Dist: attrs (>=23.1.0,<24.0.0)
Requires-Dist: boto3 (>=1.28.44,<2.0.0)
Requires-Dist: boto3-stubs[s3] (>=1.28.44,<2.0.0)
Requires-Dist: cattrs (>=23.1.2,<24.0.0)
Requires-Dist: docstring-parser (>=0.15,<0.16)
Requires-Dist: google-cloud-storage (>=2.10.0,<3.0.0)
Requires-Dist: gpt4all (>=1.0.8,<2.0.0)
Requires-Dist: jinja2 (>=3.1.2,<4.0.0)
Requires-Dist: jsonschema (>=4.19.0,<5.0.0)
Requires-Dist: openai (>=0.27.8,<0.28.0)
Requires-Dist: pydantic (>=2.3.0,<3.0.0)
Requires-Dist: redis (>=5.0.0,<6.0.0)
Requires-Dist: sentencepiece (>=0.1.99,<0.2.0)
Requires-Dist: sqlalchemy (>=2.0.20,<3.0.0)
Requires-Dist: sqlalchemy-stubs (>=0.4,<0.5)
Requires-Dist: tiktoken (>=0.4.0,<0.5.0)
Requires-Dist: tokenizers (>=0.13.3,<0.14.0)
Requires-Dist: transformers (>=4.32.1,<5.0.0)
Requires-Dist: types-google-cloud-ndb (>=2.2.0.0,<3.0.0.0)
Requires-Dist: types-redis (>=4.6.0.5,<5.0.0.0)
Project-URL: Changelog, https://github.com/nyno-ai/nynoflow/releases
Project-URL: Documentation, https://nynoflow.readthedocs.io
Project-URL: Repository, https://github.com/nyno-ai/nynoflow
